.bzrignore
CHANGES.txt
MANIFEST.in
README.txt
setup.py
tox.ini
drippy/__init__.py
drippy/tests.py
drippy.egg-info/PKG-INFO
drippy.egg-info/SOURCES.txt
drippy.egg-info/dependency_links.txt
drippy.egg-info/entry_points.txt
drippy.egg-info/requires.txt
drippy.egg-info/top_level.txt