Metadata-Version: 1.0
Name: drippy
Version: 0.3.1
Summary: Nose plugin for finding tempfile leaks
Home-page: https://launchpad.net/drippy
Author: Tres Seaver, Agendaless Consulting
Author-email: tseaver@agendaless.com
License: Python
Keywords: nose tempfile leak
Platform: Unix
Platform: Windows
Classifier: Intended Audience :: Developers
Classifier: License :: OSI Approved :: Python Software Foundation License
Classifier: Operating System :: OS Independent
Classifier: Programming Language :: Python
Classifier: Programming Language :: Python :: 2
Classifier: Programming Language :: Python :: 2.6
Classifier: Programming Language :: Python :: 2.7
Classifier: Programming Language :: Python :: 3
Classifier: Programming Language :: Python :: 3.2
Classifier: Programming Language :: Python :: 3.3
Classifier: Programming Language :: Python :: Implementation :: CPython
Classifier: Programming Language :: Python :: Implementation :: PyPy
Classifier: Topic :: Software Development :: Testing
